netcli/__init__.py
netcli/cli.py
netcli/config.py
netcli/connect.py
netcli/errors.py
netcli/formatters.py
netcli-0.0.10.dist-info/LICENSE
netcli-0.0.10.dist-info/METADATA
netcli-0.0.10.dist-info/WHEEL
netcli-0.0.10.dist-info/entry_points.txt
netcli-0.0.10.dist-info/top_level.txt
netcli-0.0.10.dist-info/RECORD
