Metadata-Version: 2.1
Name: netcli
Version: 0.0.10
Summary: The CLI that doesn't impose you any language
Home-page: UNKNOWN
Author: Christian Adell
Author-email: chadell@gmail.com
License: MIT
Keywords: Git,GitHub,automation,networking,netmiko
Platform: UNKNOWN
Classifier: Development Status :: 4 - Beta
Classifier: Environment :: Console
Classifier: Intended Audience :: Information Technology
Classifier: Intended Audience :: System Administrators
Classifier: Intended Audience :: Telecommunications Industry
Classifier: License :: OSI Approved :: MIT License
Classifier: Programming Language :: Python
Classifier: Programming Language :: Python :: 3.6
Classifier: Topic :: Internet :: WWW/HTTP
Requires-Python: >=3.5
Requires-Dist: asn1crypto (==0.24.0)
Requires-Dist: bcrypt (==3.1.6)
Requires-Dist: cffi (==1.12.2)
Requires-Dist: Click (==7.0)
Requires-Dist: colorama (==0.4.1)
Requires-Dist: cryptography (==2.4.2)
Requires-Dist: netmiko (==2.3.0)
Requires-Dist: paramiko (==2.4.2)
Requires-Dist: pyasn1 (==0.4.5)
Requires-Dist: pycparser (==2.19)
Requires-Dist: PyNaCl (==1.3.0)
Requires-Dist: pyserial (==3.4)
Requires-Dist: PyYAML (==4.2b1)
Requires-Dist: scp (==0.13.0)
Requires-Dist: six (==1.12.0)
Requires-Dist: textfsm (==0.4.1)
